setup.cfg
setup.py
seriesly/__init__.py
seriesly/core.py
seriesly/decorators.py
seriesly/exceptions.py
seriesly.egg-info/PKG-INFO
seriesly.egg-info/SOURCES.txt
seriesly.egg-info/dependency_links.txt
seriesly.egg-info/requires.txt
seriesly.egg-info/top_level.txt